{
  "cave-entrance": [
    {
      "type": "cave-entrance",
      "infoType": "cave",
      "transform": {
        "translation": {
          "x": 648,
          "y": 398
        }
      }
    }
  ],
  "candypop-red": [
    {
      "type": "candypop-red",
      "infoType": "candypop",
      "color": "red",
      "disappearsAt": 51,
      "replacedBy": "GEgg_C",
      "transform": {
        "translation": {
          "x": -454.12695,
          "y": 585.6966
        }
      }
    }
  ],
  "candypop-yellow": [
    {
      "type": "candypop-yellow",
      "infoType": "candypop",
      "color": "yellow",
      "disappearsAt": 51,
      "replacedBy": "GEgg_C",
      "transform": {
        "translation": {
          "x": -365.813,
          "y": 747.3118
        }
      }
    }
  ],
  "candypop-blue": [
    {
      "type": "candypop-blue",
      "infoType": "candypop",
      "color": "blue",
      "disappearsAt": 51,
      "replacedBy": "GEgg_C",
      "transform": {
        "translation": {
          "x": -217.15173,
          "y": 680.2527
        }
      }
    }
  ],
  "cave-exit": [
    {
      "type": "cave-exit",
      "infoType": "cave",
      "transform": {
        "translation": {
          "x": -872.5625,
          "y": 410.48254
        }
      }
    }
  ],
  "treasure": [
    {
      "type": "treasure",
      "infoType": "treasure",
      "treasureId": "OTACHERRY",
      "name": "Cupid's Grenade",
      "weight": 1,
      "carryMax": 2,
      "value": 20,
      "transform": {
        "translation": {
          "x": 205.05652,
          "y": -111.52734
        }
      }
    },
    {
      "type": "treasure",
      "infoType": "treasure",
      "treasureId": "OTACHERRY",
      "name": "Cupid's Grenade",
      "weight": 1,
      "carryMax": 2,
      "value": 20,
      "transform": {
        "translation": {
          "x": 186.0719,
          "y": 28.995605
        }
      }
    },
    {
      "type": "treasure",
      "infoType": "treasure",
      "treasureId": "OTACHERRY",
      "name": "Cupid's Grenade",
      "weight": 1,
      "carryMax": 2,
      "value": 20,
      "transform": {
        "translation": {
          "x": -245.62854,
          "y": -125.86633
        }
      }
    },
    {
      "type": "treasure",
      "infoType": "treasure",
      "treasureId": "OTAICHIGO",
      "name": "Sunseed Berry",
      "weight": 3,
      "carryMax": 6,
      "value": 70,
      "transform": {
        "translation": {
          "x": 472.2061,
          "y": 576.40576
        }
      }
    },
    {
      "type": "treasure",
      "infoType": "treasure",
      "treasureId": "OTAKIWIGLD",
      "name": "Blonde Impostor",
      "weight": 5,
      "carryMax": 10,
      "value": 40,
      "transform": {
        "translation": {
          "x": 387.81213,
          "y": 53.96753
        }
      }
    },
    {
      "type": "treasure",
      "infoType": "treasure",
      "treasureId": "OTARASPBERRY",
      "name": "Juicy Gaggle",
      "weight": 1,
      "carryMax": 2,
      "value": 20,
      "transform": {
        "translation": {
          "x": 418.48315,
          "y": 538.8856
        }
      }
    },
    {
      "type": "treasure",
      "infoType": "treasure",
      "treasureId": "OTALIME",
      "name": "Zest Bomb",
      "weight": 7,
      "carryMax": 14,
      "value": 60,
      "transform": {
        "translation": {
          "x": 310.58557,
          "y": -202.19775
        }
      }
    },
    {
      "type": "treasure",
      "infoType": "treasure",
      "treasureId": "OTAMANGO",
      "name": "Heroine's Tear",
      "weight": 12,
      "carryMax": 24,
      "value": 90,
      "transform": {
        "translation": {
          "x": -128.33704,
          "y": 267.86438
        }
      }
    },
    {
      "type": "treasure",
      "infoType": "treasure",
      "treasureId": "OTADEKOPON",
      "name": "Pocked Airhead",
      "weight": 12,
      "carryMax": 24,
      "value": 90,
      "transform": {
        "translation": {
          "x": -781.8859,
          "y": -167.55664
        }
      }
    }
  ],
  "water-water": [
    {
      "type": "water-water",
      "infoType": "water",
      "normal": {
        "image": "T_ui_Map_Cave016_F18_WaterBox00_D.png",
        "amountToFreeze": 10
      },
      "transform": {
        "translation": {
          "x": 131.75476,
          "y": -136.52808
        },
        "rotation": -20
      }
    }
  ],
  "candypop-ice": [
    {
      "type": "candypop-ice",
      "infoType": "candypop",
      "color": "ice",
      "disappearsAt": 51,
      "replacedBy": "GEgg_C",
      "transform": {
        "translation": {
          "x": 27.961426,
          "y": 675.7648
        }
      }
    }
  ],
  "candypop-white": [
    {
      "type": "candypop-white",
      "infoType": "candypop",
      "color": "white",
      "disappearsAt": 51,
      "replacedBy": "GEgg_C",
      "transform": {
        "translation": {
          "x": -117.38025,
          "y": 761.596
        }
      }
    }
  ],
  "base-onion": [
    {
      "type": "base-onion",
      "infoType": "base",
      "baseId": 0,
      "transform": {
        "translation": {
          "x": -298,
          "y": -826
        }
      }
    }
  ],
  "creature": [
    {
      "type": "creature",
      "infoType": "creature",
      "creatureId": "KURIONE",
      "name": "Honeywisp",
      "carryMax": 0,
      "value": 0,
      "seeds": 0,
      "drops": [
        {
          "item": "GHoney_C",
          "chance": 0.5,
          "min": 1,
          "max": 1
        },
        {
          "item": "GHotExtract_C",
          "chance": 0.5,
          "min": 1,
          "max": 1
        }
      ],
      "transform": {
        "translation": {
          "x": -582.87756,
          "y": -512.4513
        }
      }
    },
    {
      "type": "creature",
      "infoType": "creature",
      "creatureId": "KURIONE",
      "name": "Honeywisp",
      "carryMax": 0,
      "value": 0,
      "seeds": 0,
      "drops": [
        {
          "item": "GHoney_C",
          "chance": 0.5,
          "min": 1,
          "max": 1
        },
        {
          "item": "GHotExtract_C",
          "chance": 0.5,
          "min": 1,
          "max": 1
        }
      ],
      "transform": {
        "translation": {
          "x": -270.8645,
          "y": -595.4424
        }
      }
    },
    {
      "type": "creature",
      "infoType": "creature",
      "creatureId": "KURIONE",
      "name": "Honeywisp",
      "carryMax": 0,
      "value": 0,
      "seeds": 0,
      "drops": [
        {
          "item": "GHoney_C",
          "chance": 0.5,
          "min": 1,
          "max": 1
        },
        {
          "item": "GHotExtract_C",
          "chance": 0.5,
          "min": 1,
          "max": 1
        }
      ],
      "transform": {
        "translation": {
          "x": -385.75244,
          "y": -419.8728
        }
      }
    },
    {
      "type": "creature",
      "infoType": "creature",
      "creatureId": "KURIONE",
      "name": "Honeywisp",
      "carryMax": 0,
      "value": 0,
      "seeds": 0,
      "drops": [
        {
          "item": "GHoney_C",
          "chance": 0.5,
          "min": 1,
          "max": 1
        },
        {
          "item": "GHotExtract_C",
          "chance": 0.5,
          "min": 1,
          "max": 1
        }
      ],
      "transform": {
        "translation": {
          "x": -625.54395,
          "y": -352.177
        }
      }
    },
    {
      "type": "creature",
      "infoType": "creature",
      "creatureId": "KURIONE",
      "name": "Honeywisp",
      "carryMax": 0,
      "value": 0,
      "seeds": 0,
      "drops": [
        {
          "item": "GHoney_C",
          "chance": 0.5,
          "min": 1,
          "max": 1
        },
        {
          "item": "GHotExtract_C",
          "chance": 0.5,
          "min": 1,
          "max": 1
        }
      ],
      "transform": {
        "translation": {
          "x": -411.75037,
          "y": -91.62036
        }
      }
    },
    {
      "type": "creature",
      "infoType": "creature",
      "creatureId": "KURIONE",
      "name": "Honeywisp",
      "carryMax": 0,
      "value": 0,
      "seeds": 0,
      "drops": [
        {
          "item": "GHoney_C",
          "chance": 0.5,
          "min": 1,
          "max": 1
        },
        {
          "item": "GHotExtract_C",
          "chance": 0.5,
          "min": 1,
          "max": 1
        }
      ],
      "transform": {
        "translation": {
          "x": -411.75037,
          "y": -286.9308
        }
      }
    },
    {
      "type": "creature",
      "infoType": "creature",
      "creatureId": "KURIONE",
      "name": "Honeywisp",
      "carryMax": 0,
      "value": 0,
      "seeds": 0,
      "drops": [
        {
          "item": "GHoney_C",
          "chance": 0.5,
          "min": 1,
          "max": 1
        },
        {
          "item": "GHotExtract_C",
          "chance": 0.5,
          "min": 1,
          "max": 1
        }
      ],
      "transform": {
        "translation": {
          "x": -625.54395,
          "y": -183.90198
        }
      }
    }
  ]
}